justpid/__init__.py
tests/__init__.py
tests/context.py
tests/test_simple_pid.py
justpid-1.1.0.dist-info/METADATA
justpid-1.1.0.dist-info/WHEEL
justpid-1.1.0.dist-info/top_level.txt
justpid-1.1.0.dist-info/RECORD
