Metadata-Version: 2.1
Name: justpid
Version: 1.1.0
Summary: A simple library for pidfiles support.
Home-page: https://github.com
Author: Szymon Lipiński
Author-email: mabewlun@gmail.com
License: UNKNOWN
Project-URL: Bug Reports, https://github.com/szymonlipinski/justpid/issues
Project-URL: Source, https://github.com/szymonlipinski/justpid/
Platform: UNKNOWN
Requires-Python: >=3.6
Requires-Dist: psutil (==5.8.0)
Provides-Extra: test
Requires-Dist: black (==21.9b0) ; extra == 'test'
Requires-Dist: flake8 (==4.0.1) ; extra == 'test'
Requires-Dist: isort (==5.10.0) ; extra == 'test'
Requires-Dist: pyflakes (==2.4.0) ; extra == 'test'
Requires-Dist: pytest (==6.2.5) ; extra == 'test'
Requires-Dist: cohesion (==1.0.0) ; extra == 'test'
Requires-Dist: flake8-functions (==0.0.6) ; extra == 'test'
Requires-Dist: flake8-expression-complexity (==0.0.9) ; extra == 'test'
Requires-Dist: flake8-alphabetize (==0.0.16) ; extra == 'test'
Requires-Dist: flake8-bugbear (==21.9.2) ; extra == 'test'
Requires-Dist: flake8-builtins (==1.5.3) ; extra == 'test'
Requires-Dist: flake8-pytest-style (==1.5.1) ; extra == 'test'
Requires-Dist: flake8-return (==1.1.3) ; extra == 'test'
Requires-Dist: flake8-simplify (==0.14.2) ; extra == 'test'
